{
    "description": "HyperBar",
    "manipulators": [
        {
            "from": {
                "key_code": "spacebar",
                "modifiers": { "optional": ["any"] }
            },
            "to_if_alone": [{ "key_code": "spacebar" }],
            "to_if_held_down": [
                {
                    "key_code": "left_shift",
                    "modifiers": ["left_command", "left_control", "left_option"]
                }
            ],
            "type": "basic"
        }
    ]
}
